{
  "profileDir": "C:\\Users\\andyf\\andy2_crawler\\profiles\\automation-profile",
  "outputPath": "C:\\Users\\andyf\\andy2_crawler\\data\\crawl-store.json",
  "chrome": {
    "useSystemProfile": true,
    "mode": "cdp"
  },
  "targets": [],
  "siteRules": {
    "xCom": {
      "maxChars": 40000,
      "maxCharsPerComment": 700,
      "contentLevel": "feed",
      "stallLimit": 3,
      "maxAgeDays": 35
    },
    "redditCom": {
      "maxChars": 40000,
      "maxCharsPerComment": 900,
      "contentLevel": "post",
      "stallLimit": 3,
      "maxFeedScrolls": 5,
      "maxAgeDays": 35
    },
    "bloombergCom": {
      "maxChars": 20000,
      "maxCharsPerComment": 600,
      "contentLevel": "post",
      "stallLimit": 3,
      "maxAgeDays": 35
    }
  },
  "behavior": {
    "navigationTimeoutMs": 45000,
    "waitMinMs": 2500,
    "waitMaxMs": 6000,
    "retriesPerTarget": 1,
    "maxPagesPerRun": 6
  },
  "schedule": {
    "enabled": false,
    "intervalMs": 300000,
    "maxRuns": 10
  },
  "clipboard": {
    "maxChars": 200000
  },
  "dedup": {
    "windowDays": 5
  },
  "feeds": {
    "enabled": true,
    "maxAgeDays": 7,
    "globenewswire": { "enabled": true, "maxChars": 20000 },
    "googleNews": { "enabled": true, "maxChars": 20000 },
    "edgar": { "enabled": false, "maxChars": 20000, "formTypes": ["8-K"] }
  },
  "backend": {
    "enabled": true,
    "baseUrl": "https://a1a2-command-center.onrender.com"
  }
}
